README.txt
setup.cfg
setup.py
docs/HISTORY.txt
docs/LICENSE.GPL
docs/LICENSE.txt
docs/MANUAL.txt
raptus/__init__.py
raptus.article.hidecolumns.egg-info/PKG-INFO
raptus.article.hidecolumns.egg-info/SOURCES.txt
raptus.article.hidecolumns.egg-info/dependency_links.txt
raptus.article.hidecolumns.egg-info/entry_points.txt
raptus.article.hidecolumns.egg-info/namespace_packages.txt
raptus.article.hidecolumns.egg-info/not-zip-safe
raptus.article.hidecolumns.egg-info/requires.txt
raptus.article.hidecolumns.egg-info/top_level.txt
raptus/article/__init__.py
raptus/article/hidecolumns/__init__.py
raptus/article/hidecolumns/configure.zcml
raptus/article/hidecolumns/extender.py
raptus/article/hidecolumns/manager.py
raptus/article/hidecolumns/overrides.zcml
raptus/article/hidecolumns/i18n/raptus.article-de.po
raptus/article/hidecolumns/i18n/raptus.article-fr.po
raptus/article/hidecolumns/i18n/raptus.article.pot