Metadata-Version: 1.0
Name: raptus.article.hidecolumns
Version: 2.0b5
Summary: Provides functionality to hide the left or right portlet column per article
Home-page: http://raptus.com
Author: Raptus AG
Author-email: dev@raptus.com
License: GPL
Platform: UNKNOWN
Classifier: Programming Language :: Python
Classifier: Topic :: Software Development :: Libraries :: Python Modules
